README.rst
setup.cfg
setup.py
src/toil/__init__.py
src/toil/common.py
src/toil/fileStore.py
src/toil/job.py
src/toil/jobGraph.py
src/toil/leader.py
src/toil/realtimeLogger.py
src/toil/resource.py
src/toil/serviceManager.py
src/toil/statsAndLogging.py
src/toil/toilState.py
src/toil/version.py
src/toil/worker.py
src/toil/batchSystems/__init__.py
src/toil/batchSystems/abstractBatchSystem.py
src/toil/batchSystems/abstractGridEngineBatchSystem.py
src/toil/batchSystems/gridengine.py
src/toil/batchSystems/htcondor.py
src/toil/batchSystems/lsf.py
src/toil/batchSystems/lsfHelper.py
src/toil/batchSystems/options.py
src/toil/batchSystems/parasol.py
src/toil/batchSystems/parasolTestSupport.py
src/toil/batchSystems/registry.py
src/toil/batchSystems/singleMachine.py
src/toil/batchSystems/slurm.py
src/toil/batchSystems/torque.py
src/toil/batchSystems/mesos/__init__.py
src/toil/batchSystems/mesos/batchSystem.py
src/toil/batchSystems/mesos/conftest.py
src/toil/batchSystems/mesos/executor.py
src/toil/batchSystems/mesos/test/__init__.py
src/toil/cwl/__init__.py
src/toil/cwl/conftest.py
src/toil/cwl/cwltoil.py
src/toil/jobStores/__init__.py
src/toil/jobStores/abstractJobStore.py
src/toil/jobStores/azureJobStore.py
src/toil/jobStores/conftest.py
src/toil/jobStores/fileJobStore.py
src/toil/jobStores/googleJobStore.py
src/toil/jobStores/utils.py
src/toil/jobStores/aws/__init__.py
src/toil/jobStores/aws/jobStore.py
src/toil/jobStores/aws/utils.py
src/toil/lib/__init__.py
src/toil/lib/bioio.py
src/toil/lib/context.py
src/toil/lib/docker.py
src/toil/lib/ec2.py
src/toil/lib/ec2nodes.py
src/toil/lib/exceptions.py
src/toil/lib/expando.py
src/toil/lib/fnmatch.py
src/toil/lib/generatedEC2Lists.py
src/toil/lib/humanize.py
src/toil/lib/iterables.py
src/toil/lib/memoize.py
src/toil/lib/message.py
src/toil/lib/misc.py
src/toil/lib/objects.py
src/toil/lib/retry.py
src/toil/lib/threading.py
src/toil/lib/throttle.py
src/toil/lib/encryption/__init__.py
src/toil/lib/encryption/_dummy.py
src/toil_ionox0.egg-info/PKG-INFO
src/toil_ionox0.egg-info/SOURCES.txt
src/toil_ionox0.egg-info/dependency_links.txt
src/toil_ionox0.egg-info/entry_points.txt
src/toil_ionox0.egg-info/requires.txt
src/toil_ionox0.egg-info/top_level.txt