Metadata-Version: 2.1
Name: toil-ionox0
Version: 0.0.10
Summary: Pipeline management software for clusters.
Home-page: https://github.com/ionox0/toil/tree/ij/toil-ionox0
Author: Benedict Paten
Author-email: ionox0@gmail.com
License: Apache License v2.0
Platform: UNKNOWN
Classifier: License :: OSI Approved :: Apache Software License
Provides-Extra: all
Provides-Extra: google
Provides-Extra: mesos
Provides-Extra: encryption
Provides-Extra: aws
Provides-Extra: wdl
Provides-Extra: htcondor
Provides-Extra: cwl
Provides-Extra: azure
